gdb_brexazine/__init__.py
gdb_brexazine/cli.py
gdb_brexazine/gdb_brexazine.py
gdb_brexazine-0.1.0.dist-info/AUTHORS.rst
gdb_brexazine-0.1.0.dist-info/LICENSE
gdb_brexazine-0.1.0.dist-info/METADATA
gdb_brexazine-0.1.0.dist-info/WHEEL
gdb_brexazine-0.1.0.dist-info/top_level.txt
gdb_brexazine-0.1.0.dist-info/RECORD
