Metadata-Version: 2.1
Name: gdb_brexazine
Version: 0.1.0
Summary: Diamonds in Chemical Space: the Synthesis of Brexazine
Author-email: Ye Buehler <ye.buehler-feng@unibe.ch>
Maintainer-email: Ye Buehler <ye.buehler-feng@unibe.ch>
License: MIT license
Project-URL: bugs, https://github.com/Ye-Buehler/gdb_brexazine/issues
Project-URL: changelog, https://github.com/Ye-Buehler/gdb_brexazine/blob/master/changelog.md
Project-URL: homepage, https://github.com/Ye-Buehler/gdb_brexazine
License-File: LICENSE
License-File: AUTHORS.rst
Requires-Dist: typer
Provides-Extra: dev
Requires-Dist: coverage ; extra == 'dev'
Requires-Dist: mypy ; extra == 'dev'
Requires-Dist: pytest ; extra == 'dev'
Requires-Dist: ruff ; extra == 'dev'
